MANIFEST.in
account_tax.xml
account_tax_code.xml
l10n_bo_chart.xml
l10n_bo_wizard.xml
setup.py
./__init__.py
./__openerp__.py
i18n/en_GB.po
i18n/es.po
i18n/es_BO.po
i18n/it.po
i18n/l10n_bo.pot
i18n/nl.po
i18n/pt.po
i18n/pt_BR.po
i18n/sl.po
i18n/tr.po
openerp_l10n_bo.egg-info/PKG-INFO
openerp_l10n_bo.egg-info/SOURCES.txt
openerp_l10n_bo.egg-info/dependency_links.txt
openerp_l10n_bo.egg-info/requires.txt
openerp_l10n_bo.egg-info/top_level.txt
static/src/img/icon.png